[
    {
        "title": "Алита: Боевой Ангел",
        "date": "Фев 14, 2019",
        "country": "США",
        "rating": "IMDB: 7.4/10",
        "description": "Деактивированный киборг возрождается, но не может ничего вспомнить из своей прошлой жизни и отправляется на поиски, чтобы узнать, кто она такая.",
        "img": "https://m.media-amazon.com/images/M/MV5BMTQzYWYwYjctY2JhZS00NTYzLTllM2UtZWY5ZTk0NmYwYzIyXkEyXkFqcGdeQXVyMzgxODM4NjM@._V1_.jpg",
        "actors": "Роза Салазар, Кристоф Вальц, Дженнифер Коннелли, Махершала Али, Эд Скрейн, Джеки Эрл Хейли",
        "director": "Роберт Родригес",
        "trailer_link": "https://www.youtube.com/watch?v=w7pYhpJaJW8&ab_channel=20thCenturyStudios"
    }
]